<?xml version="1.0" encoding="utf-8"?>
<ArrayOfAObjectType xmlns:xsi="http://www.w3.org/2001/XMLSchema-instance" xmlns:xsd="http://www.w3.org/2001/XMLSchema">
  <AObjectType>
    <DataTypeName>empty</DataTypeName>
    <DataTypeSize>0</DataTypeSize>
    <FunctionName>empty</FunctionName>
    <Template>empty</Template>
    <Attributes />
    <DTProperties />
    <GalaxyAttributes />
  </AObjectType>
  <AObjectType>
    <DataTypeName>AinData</DataTypeName>
    <DataTypeSize>44</DataTypeSize>
    <FunctionName>Ain</FunctionName>
    <Template>AIS</Template>
    <Attributes>
      <ATopicParametr>
        <AttributeName>IFCDW0</AttributeName>
        <DataType>D0</DataType>
      </ATopicParametr>
      <ATopicParametr>
        <AttributeName>IFCW4</AttributeName>
        <DataType>W4</DataType>
      </ATopicParametr>
      <ATopicParametr>
        <AttributeName>IFCW6</AttributeName>
        <DataType>W6</DataType>
      </ATopicParametr>
      <ATopicParametr>
        <AttributeName>IFCDW8</AttributeName>
        <DataType>REAL8</DataType>
      </ATopicParametr>
      <ATopicParametr>
        <AttributeName>IFCDW12</AttributeName>
        <DataType>REAL12</DataType>
      </ATopicParametr>
      <ATopicParametr>
        <AttributeName>IFCDW16</AttributeName>
        <DataType>REAL16</DataType>
      </ATopicParametr>
      <ATopicParametr>
        <AttributeName>IFCDW20</AttributeName>
        <DataType>REAL20</DataType>
      </ATopicParametr>
      <ATopicParametr>
        <AttributeName>IFCDW24</AttributeName>
        <DataType>REAL24</DataType>
      </ATopicParametr>
      <ATopicParametr>
        <AttributeName>IFCDW28</AttributeName>
        <DataType>REAL28</DataType>
      </ATopicParametr>
      <ATopicParametr>
        <AttributeName>IFCDW32</AttributeName>
        <DataType>REAL32</DataType>
      </ATopicParametr>
    </Attributes>
    <DTProperties>
      <DataTypeProperties>
        <propertyName>Bipolar</propertyName>
        <propertyColumn>Bipolar</propertyColumn>
      </DataTypeProperties>
      <DataTypeProperties>
        <propertyName>Max</propertyName>
        <propertyColumn>MAX</propertyColumn>
      </DataTypeProperties>
      <DataTypeProperties>
        <propertyName>Min</propertyName>
        <propertyColumn>MIN</propertyColumn>
      </DataTypeProperties>
      <DataTypeProperties>
        <propertyName>AlarmInitDelayHH</propertyName>
        <propertyColumn>Init_HH_Dly</propertyColumn>
      </DataTypeProperties>
      <DataTypeProperties>
        <propertyName>AlarmInitDelayH</propertyName>
        <propertyColumn>Init_H_Dly</propertyColumn>
      </DataTypeProperties>
      <DataTypeProperties>
        <propertyName>AlarmInitDelayL</propertyName>
        <propertyColumn>Init_L_Dly</propertyColumn>
      </DataTypeProperties>
      <DataTypeProperties>
        <propertyName>AlarmInitDelayLL</propertyName>
        <propertyColumn>Init_LL_Dly</propertyColumn>
      </DataTypeProperties>
      <DataTypeProperties>
        <propertyName>AEDeadBand</propertyName>
        <propertyColumn>AL_DB</propertyColumn>
      </DataTypeProperties>
      <DataTypeProperties>
        <propertyName>AEConfigHH</propertyName>
        <propertyColumn>AE_HH_Cfg</propertyColumn>
      </DataTypeProperties>
      <DataTypeProperties>
        <propertyName>AELevelHH</propertyName>
        <propertyColumn>Init_HH_Lvl</propertyColumn>
      </DataTypeProperties>
      <DataTypeProperties>
        <propertyName>AEConfigH</propertyName>
        <propertyColumn>AE_H_Cfg</propertyColumn>
      </DataTypeProperties>
      <DataTypeProperties>
        <propertyName>AELevelH</propertyName>
        <propertyColumn>Init_H_Lvl</propertyColumn>
      </DataTypeProperties>
      <DataTypeProperties>
        <propertyName>AEConfigL</propertyName>
        <propertyColumn>AE_L_Cfg</propertyColumn>
      </DataTypeProperties>
      <DataTypeProperties>
        <propertyName>AELevelL</propertyName>
        <propertyColumn>Init_L_Lvl</propertyColumn>
      </DataTypeProperties>
      <DataTypeProperties>
        <propertyName>AEConfigLL</propertyName>
        <propertyColumn>AE_LL_Cfg</propertyColumn>
      </DataTypeProperties>
      <DataTypeProperties>
        <propertyName>AELevelLL</propertyName>
        <propertyColumn>Init_LL_Lvl</propertyColumn>
      </DataTypeProperties>
      <DataTypeProperties>
        <propertyName>LIO</propertyName>
        <propertyColumn>DBName + TagName</propertyColumn>
      </DataTypeProperties>
    </DTProperties>
    <GalaxyAttributes>
      <AGalaxyParametr>
        <AttributeName>TagName</AttributeName>
        <propertyColumn>TagName</propertyColumn>
      </AGalaxyParametr>
      <AGalaxyParametr>
        <AttributeName>ObjectDescription</AttributeName>
        <propertyColumn>Descr</propertyColumn>
      </AGalaxyParametr>
      <AGalaxyParametr>
        <AttributeName>Area</AttributeName>
        <propertyColumn>HMIArea</propertyColumn>
      </AGalaxyParametr>
      <AGalaxyParametr>
        <AttributeName>Container</AttributeName>
        <propertyColumn>HMIparrent</propertyColumn>
      </AGalaxyParametr>
      <AGalaxyParametr>
        <AttributeName>HMI_SigAlarmHH.Priority</AttributeName>
        <propertyColumn>AEHH_severity</propertyColumn>
      </AGalaxyParametr>
      <AGalaxyParametr>
        <AttributeName>HMI_SigAlarmH.Priority</AttributeName>
        <propertyColumn>AEH_severity</propertyColumn>
      </AGalaxyParametr>
      <AGalaxyParametr>
        <AttributeName>HMI_SigAlarmL.Priority</AttributeName>
        <propertyColumn>AEL_severity</propertyColumn>
      </AGalaxyParametr>
      <AGalaxyParametr>
        <AttributeName>HMI_SigAlarmLL.Priority</AttributeName>
        <propertyColumn>AELL_severity</propertyColumn>
      </AGalaxyParametr>
      <AGalaxyParametr>
        <AttributeName>HMI_HWSigFault.Priority</AttributeName>
        <propertyColumn>HMI_HWSigFault_severity</propertyColumn>
      </AGalaxyParametr>
      <AGalaxyParametr>
        <AttributeName>ValueDecimalPlaces</AttributeName>
        <propertyColumn>ValueDecimalPlaces</propertyColumn>
      </AGalaxyParametr>
      <AGalaxyParametr>
        <AttributeName>SecurityDefinition</AttributeName>
        <propertyColumn>SecurityDefinition</propertyColumn>
      </AGalaxyParametr>
      <AGalaxyParametr>
        <AttributeName>IFCDW8.EngUnits</AttributeName>
        <propertyColumn>Unit</propertyColumn>
      </AGalaxyParametr>
    </GalaxyAttributes>
  </AObjectType>
  <AObjectType>
    <DataTypeName>AnalogPosCtrlData</DataTypeName>
    <DataTypeSize>62</DataTypeSize>
    <FunctionName>AnalogPosCtrl</FunctionName>
    <Template>AnalogPos</Template>
    <Attributes>
      <ATopicParametr>
        <AttributeName>IFCDW0</AttributeName>
        <DataType>D0</DataType>
      </ATopicParametr>
      <ATopicParametr>
        <AttributeName>IFCW4</AttributeName>
        <DataType>W4</DataType>
      </ATopicParametr>
      <ATopicParametr>
        <AttributeName>IFCW6</AttributeName>
        <DataType>W6</DataType>
      </ATopicParametr>
      <ATopicParametr>
        <AttributeName>IFCDW8</AttributeName>
        <DataType>REAL8</DataType>
      </ATopicParametr>
      <ATopicParametr>
        <AttributeName>IFCDW12</AttributeName>
        <DataType>REAL12</DataType>
      </ATopicParametr>
      <ATopicParametr>
        <AttributeName>IFCDW16</AttributeName>
        <DataType>REAL16</DataType>
      </ATopicParametr>
      <ATopicParametr>
        <AttributeName>IFCDW20</AttributeName>
        <DataType>REAL20</DataType>
      </ATopicParametr>
      <ATopicParametr>
        <AttributeName>IFCDW24</AttributeName>
        <DataType>REAL24</DataType>
      </ATopicParametr>
    </Attributes>
    <DTProperties>
      <DataTypeProperties>
        <propertyName>FBConf</propertyName>
        <propertyColumn>FBConfig</propertyColumn>
      </DataTypeProperties>
      <DataTypeProperties>
        <propertyName>Bipolar</propertyName>
        <propertyColumn>Bipolar</propertyColumn>
      </DataTypeProperties>
      <DataTypeProperties>
        <propertyName>LIO</propertyName>
        <propertyColumn>DBName + TagName</propertyColumn>
      </DataTypeProperties>
    </DTProperties>
    <GalaxyAttributes>
      <AGalaxyParametr>
        <AttributeName>TagName</AttributeName>
        <propertyColumn>TagName</propertyColumn>
      </AGalaxyParametr>
      <AGalaxyParametr>
        <AttributeName>ObjectDescription</AttributeName>
        <propertyColumn>Descr</propertyColumn>
      </AGalaxyParametr>
      <AGalaxyParametr>
        <AttributeName>Area</AttributeName>
        <propertyColumn>HMIArea</propertyColumn>
      </AGalaxyParametr>
      <AGalaxyParametr>
        <AttributeName>Container</AttributeName>
        <propertyColumn>HMIparrent</propertyColumn>
      </AGalaxyParametr>
      <AGalaxyParametr>
        <AttributeName>HMI_HWSigFault.Priority</AttributeName>
        <propertyColumn>HMI_HWSigFault_severity</propertyColumn>
      </AGalaxyParametr>
      <AGalaxyParametr>
        <AttributeName>ValueDecimalPlaces</AttributeName>
        <propertyColumn>ValueDecimalPlaces</propertyColumn>
      </AGalaxyParametr>
      <AGalaxyParametr>
        <AttributeName>SecurityDefinition</AttributeName>
        <propertyColumn>SecurityDefinition</propertyColumn>
      </AGalaxyParametr>
      <AGalaxyParametr>
        <AttributeName>Me.IFCDW12.EngUnits</AttributeName>
        <propertyColumn>Unit</propertyColumn>
      </AGalaxyParametr>
    </GalaxyAttributes>
  </AObjectType>
  <AObjectType>
    <DataTypeName>AoutData</DataTypeName>
    <DataTypeSize>24</DataTypeSize>
    <FunctionName>Aout</FunctionName>
    <Template>AOS</Template>
    <Attributes>
      <ATopicParametr>
        <AttributeName>IFCW0</AttributeName>
        <DataType>W0</DataType>
      </ATopicParametr>
      <ATopicParametr>
        <AttributeName>IFCDW4</AttributeName>
        <DataType>REAL4</DataType>
      </ATopicParametr>
      <ATopicParametr>
        <AttributeName>IFCDW8</AttributeName>
        <DataType>REAL8</DataType>
      </ATopicParametr>
      <ATopicParametr>
        <AttributeName>IFCDW12</AttributeName>
        <DataType>REAL12</DataType>
      </ATopicParametr>
    </Attributes>
    <DTProperties>
      <DataTypeProperties>
        <propertyName>Bipolar</propertyName>
        <propertyColumn>Bipolar</propertyColumn>
      </DataTypeProperties>
      <DataTypeProperties>
        <propertyName>Max</propertyName>
        <propertyColumn>MAX</propertyColumn>
      </DataTypeProperties>
      <DataTypeProperties>
        <propertyName>Min</propertyName>
        <propertyColumn>MIN</propertyColumn>
      </DataTypeProperties>
      <DataTypeProperties>
        <propertyName>LIO</propertyName>
        <propertyColumn>DBName + TagName</propertyColumn>
      </DataTypeProperties>
    </DTProperties>
    <GalaxyAttributes>
      <AGalaxyParametr>
        <AttributeName>TagName</AttributeName>
        <propertyColumn>TagName</propertyColumn>
      </AGalaxyParametr>
      <AGalaxyParametr>
        <AttributeName>ObjectDescription</AttributeName>
        <propertyColumn>Descr</propertyColumn>
      </AGalaxyParametr>
      <AGalaxyParametr>
        <AttributeName>Area</AttributeName>
        <propertyColumn>HMIArea</propertyColumn>
      </AGalaxyParametr>
      <AGalaxyParametr>
        <AttributeName>Container</AttributeName>
        <propertyColumn>HMIparrent</propertyColumn>
      </AGalaxyParametr>
      <AGalaxyParametr>
        <AttributeName>HMI_HWSigFault.Priority</AttributeName>
        <propertyColumn>HMI_HWSigFault_severity</propertyColumn>
      </AGalaxyParametr>
      <AGalaxyParametr>
        <AttributeName>ValueDecimalPlaces</AttributeName>
        <propertyColumn>ValueDecimalPlaces</propertyColumn>
      </AGalaxyParametr>
      <AGalaxyParametr>
        <AttributeName>SecurityDefinition</AttributeName>
        <propertyColumn>SecurityDefinition</propertyColumn>
      </AGalaxyParametr>
      <AGalaxyParametr>
        <AttributeName>IFCDW4.EngUnits</AttributeName>
        <propertyColumn>Unit</propertyColumn>
      </AGalaxyParametr>
    </GalaxyAttributes>
  </AObjectType>
  <AObjectType>
    <DataTypeName>DinData</DataTypeName>
    <DataTypeSize>6</DataTypeSize>
    <FunctionName>Din</FunctionName>
    <Template>DIS</Template>
    <Attributes>
      <ATopicParametr>
        <AttributeName>IFCW0</AttributeName>
        <DataType>W0</DataType>
      </ATopicParametr>
      <ATopicParametr>
        <AttributeName>IFCW2</AttributeName>
        <DataType>W2</DataType>
      </ATopicParametr>
    </Attributes>
    <DTProperties>
      <DataTypeProperties>
        <propertyName>NoramalState</propertyName>
        <propertyColumn>NormalState</propertyColumn>
      </DataTypeProperties>
      <DataTypeProperties>
        <propertyName>AEConfig</propertyName>
        <propertyColumn>AEConfigDiff</propertyColumn>
      </DataTypeProperties>
      <DataTypeProperties>
        <propertyName>AlarmDelay</propertyName>
        <propertyColumn>Alarm_InitDelay</propertyColumn>
      </DataTypeProperties>
      <DataTypeProperties>
        <propertyName>LIO</propertyName>
        <propertyColumn>DBName + TagName</propertyColumn>
      </DataTypeProperties>
    </DTProperties>
    <GalaxyAttributes>
      <AGalaxyParametr>
        <AttributeName>TagName</AttributeName>
        <propertyColumn>TagName</propertyColumn>
      </AGalaxyParametr>
      <AGalaxyParametr>
        <AttributeName>ObjectDescription</AttributeName>
        <propertyColumn>Descr</propertyColumn>
      </AGalaxyParametr>
      <AGalaxyParametr>
        <AttributeName>Area</AttributeName>
        <propertyColumn>HMIArea</propertyColumn>
      </AGalaxyParametr>
      <AGalaxyParametr>
        <AttributeName>Container</AttributeName>
        <propertyColumn>HMIparrent</propertyColumn>
      </AGalaxyParametr>
      <AGalaxyParametr>
        <AttributeName>HMI_SigAlarm.Priority</AttributeName>
        <propertyColumn>AESeverity</propertyColumn>
      </AGalaxyParametr>
      <AGalaxyParametr>
        <AttributeName>SecurityDefinition</AttributeName>
        <propertyColumn>SecurityDefinition</propertyColumn>
      </AGalaxyParametr>
    </GalaxyAttributes>
  </AObjectType>
  <AObjectType>
    <DataTypeName>DoutData</DataTypeName>
    <DataTypeSize>6</DataTypeSize>
    <FunctionName>Dout</FunctionName>
    <Template>DOS</Template>
    <Attributes>
      <ATopicParametr>
        <AttributeName>IFCW0</AttributeName>
        <DataType>W0</DataType>
      </ATopicParametr>
      <ATopicParametr>
        <AttributeName>IFCW2</AttributeName>
        <DataType>W2</DataType>
      </ATopicParametr>
    </Attributes>
    <DTProperties>
      <DataTypeProperties>
        <propertyName>PulseTime</propertyName>
        <propertyColumn>PulseTime</propertyColumn>
      </DataTypeProperties>
      <DataTypeProperties>
        <propertyName>LIO</propertyName>
        <propertyColumn>DBName + TagName</propertyColumn>
      </DataTypeProperties>
    </DTProperties>
    <GalaxyAttributes>
      <AGalaxyParametr>
        <AttributeName>TagName</AttributeName>
        <propertyColumn>TagName</propertyColumn>
      </AGalaxyParametr>
      <AGalaxyParametr>
        <AttributeName>ObjectDescription</AttributeName>
        <propertyColumn>Descr</propertyColumn>
      </AGalaxyParametr>
      <AGalaxyParametr>
        <AttributeName>Area</AttributeName>
        <propertyColumn>HMIArea</propertyColumn>
      </AGalaxyParametr>
      <AGalaxyParametr>
        <AttributeName>Container</AttributeName>
        <propertyColumn>HMIparrent</propertyColumn>
      </AGalaxyParametr>
      <AGalaxyParametr>
        <AttributeName>SecurityDefinition</AttributeName>
        <propertyColumn>SecurityDefinition</propertyColumn>
      </AGalaxyParametr>
    </GalaxyAttributes>
  </AObjectType>
  <AObjectType>
    <DataTypeName>GrpCycData</DataTypeName>
    <DataTypeSize>14</DataTypeSize>
    <FunctionName>GrpCycCtrl</FunctionName>
    <Template>GrpCycCtrl</Template>
    <Attributes>
      <ATopicParametr>
        <AttributeName>IFCDW0</AttributeName>
        <DataType>D0</DataType>
      </ATopicParametr>
      <ATopicParametr>
        <AttributeName>IFCW4</AttributeName>
        <DataType>W4</DataType>
      </ATopicParametr>
      <ATopicParametr>
        <AttributeName>IFCDW6</AttributeName>
        <DataType>REAL6</DataType>
      </ATopicParametr>
      <ATopicParametr>
        <AttributeName>IFCDW10</AttributeName>
        <DataType>REAL10</DataType>
      </ATopicParametr>
    </Attributes>
    <DTProperties>
      <DataTypeProperties>
        <propertyName>StepQty</propertyName>
        <propertyColumn>StepQty</propertyColumn>
      </DataTypeProperties>
      <DataTypeProperties>
        <propertyName>SeqRep</propertyName>
        <propertyColumn>SeqRep</propertyColumn>
      </DataTypeProperties>
      <DataTypeProperties>
        <propertyName>LIO</propertyName>
        <propertyColumn>DBName + TagName</propertyColumn>
      </DataTypeProperties>
    </DTProperties>
    <GalaxyAttributes>
      <AGalaxyParametr>
        <AttributeName>TagName</AttributeName>
        <propertyColumn>TagName</propertyColumn>
      </AGalaxyParametr>
      <AGalaxyParametr>
        <AttributeName>ObjectDescription</AttributeName>
        <propertyColumn>Descr</propertyColumn>
      </AGalaxyParametr>
      <AGalaxyParametr>
        <AttributeName>Area</AttributeName>
        <propertyColumn>HMIArea</propertyColumn>
      </AGalaxyParametr>
      <AGalaxyParametr>
        <AttributeName>Container</AttributeName>
        <propertyColumn>HMIparrent</propertyColumn>
      </AGalaxyParametr>
      <AGalaxyParametr>
        <AttributeName>SecurityDefinition</AttributeName>
        <propertyColumn>SecurityDefinition</propertyColumn>
      </AGalaxyParametr>
    </GalaxyAttributes>
  </AObjectType>
  <AObjectType>
    <DataTypeName>GrpData</DataTypeName>
    <DataTypeSize>30</DataTypeSize>
    <FunctionName>GrpCtrl</FunctionName>
    <Template>GrpCtrl	</Template>
    <Attributes>
      <ATopicParametr>
        <AttributeName>IFCW0</AttributeName>
        <DataType>W0</DataType>
      </ATopicParametr>
      <ATopicParametr>
        <AttributeName>IFCW2</AttributeName>
        <DataType>W2</DataType>
      </ATopicParametr>
      <ATopicParametr>
        <AttributeName>IFCW4</AttributeName>
        <DataType>W4</DataType>
      </ATopicParametr>
      <ATopicParametr>
        <AttributeName>IFCW6</AttributeName>
        <DataType>W6</DataType>
      </ATopicParametr>
    </Attributes>
    <DTProperties />
    <GalaxyAttributes>
      <AGalaxyParametr>
        <AttributeName>TagName</AttributeName>
        <propertyColumn>TagName</propertyColumn>
      </AGalaxyParametr>
      <AGalaxyParametr>
        <AttributeName>ObjectDescription</AttributeName>
        <propertyColumn>Descr</propertyColumn>
      </AGalaxyParametr>
      <AGalaxyParametr>
        <AttributeName>Area</AttributeName>
        <propertyColumn>HMIArea</propertyColumn>
      </AGalaxyParametr>
      <AGalaxyParametr>
        <AttributeName>Container</AttributeName>
        <propertyColumn>HMIparrent</propertyColumn>
      </AGalaxyParametr>
      <AGalaxyParametr>
        <AttributeName>SecurityDefinition</AttributeName>
        <propertyColumn>SecurityDefinition</propertyColumn>
      </AGalaxyParametr>
    </GalaxyAttributes>
  </AObjectType>
  <AObjectType>
    <DataTypeName>OnOffCtrlData</DataTypeName>
    <DataTypeSize>20</DataTypeSize>
    <FunctionName>OnOffCtrl</FunctionName>
    <Template>OnOffCtrl</Template>
    <Attributes>
      <ATopicParametr>
        <AttributeName>IFCDW0</AttributeName>
        <DataType>D0</DataType>
      </ATopicParametr>
      <ATopicParametr>
        <AttributeName>IFCDW4</AttributeName>
        <DataType>D4</DataType>
      </ATopicParametr>
      <ATopicParametr>
        <AttributeName>IFCW8</AttributeName>
        <DataType>W8</DataType>
      </ATopicParametr>
    </Attributes>
    <DTProperties>
      <DataTypeProperties>
        <propertyName>IBF</propertyName>
        <propertyColumn>IBF</propertyColumn>
      </DataTypeProperties>
      <DataTypeProperties>
        <propertyName>EnAuto</propertyName>
        <propertyColumn>EnAuto</propertyColumn>
      </DataTypeProperties>
      <DataTypeProperties>
        <propertyName>FBConfig</propertyName>
        <propertyColumn>FBConfig</propertyColumn>
      </DataTypeProperties>
      <DataTypeProperties>
        <propertyName>LIO</propertyName>
        <propertyColumn>DBName + TagName</propertyColumn>
      </DataTypeProperties>
    </DTProperties>
    <GalaxyAttributes>
      <AGalaxyParametr>
        <AttributeName>TagName</AttributeName>
        <propertyColumn>TagName</propertyColumn>
      </AGalaxyParametr>
      <AGalaxyParametr>
        <AttributeName>ObjectDescription</AttributeName>
        <propertyColumn>Descr</propertyColumn>
      </AGalaxyParametr>
      <AGalaxyParametr>
        <AttributeName>Area</AttributeName>
        <propertyColumn>HMIArea</propertyColumn>
      </AGalaxyParametr>
      <AGalaxyParametr>
        <AttributeName>Container</AttributeName>
        <propertyColumn>HMIparrent</propertyColumn>
      </AGalaxyParametr>
      <AGalaxyParametr>
        <AttributeName>SecurityDefinition</AttributeName>
        <propertyColumn>SecurityDefinition</propertyColumn>
      </AGalaxyParametr>
    </GalaxyAttributes>
  </AObjectType>
  <AObjectType>
    <DataTypeName>OnOffCtrlData_2D</DataTypeName>
    <DataTypeSize>26</DataTypeSize>
    <FunctionName>OnOffCtrl_2D</FunctionName>
    <Template>OnOffCtrl_2D</Template>
    <Attributes>
      <ATopicParametr>
        <AttributeName>IFCDW0</AttributeName>
        <DataType>D0</DataType>
      </ATopicParametr>
      <ATopicParametr>
        <AttributeName>IFCDW4</AttributeName>
        <DataType>D2</DataType>
      </ATopicParametr>
      <ATopicParametr>
        <AttributeName>IFCDW8</AttributeName>
        <DataType>D4</DataType>
      </ATopicParametr>
      <ATopicParametr>
        <AttributeName>IFCW12</AttributeName>
        <DataType>W12</DataType>
      </ATopicParametr>
    </Attributes>
    <DTProperties>
      <DataTypeProperties>
        <propertyName>IBF</propertyName>
        <propertyColumn>IBF</propertyColumn>
      </DataTypeProperties>
      <DataTypeProperties>
        <propertyName>EnAuto</propertyName>
        <propertyColumn>EnAuto</propertyColumn>
      </DataTypeProperties>
      <DataTypeProperties>
        <propertyName>FBConf</propertyName>
        <propertyColumn>FBConfig</propertyColumn>
      </DataTypeProperties>
      <DataTypeProperties>
        <propertyName>LIO</propertyName>
        <propertyColumn>DBName + TagName</propertyColumn>
      </DataTypeProperties>
    </DTProperties>
    <GalaxyAttributes>
      <AGalaxyParametr>
        <AttributeName>TagName</AttributeName>
        <propertyColumn>TagName</propertyColumn>
      </AGalaxyParametr>
      <AGalaxyParametr>
        <AttributeName>ObjectDescription</AttributeName>
        <propertyColumn>Descr</propertyColumn>
      </AGalaxyParametr>
      <AGalaxyParametr>
        <AttributeName>Area</AttributeName>
        <propertyColumn>HMIArea</propertyColumn>
      </AGalaxyParametr>
      <AGalaxyParametr>
        <AttributeName>Container</AttributeName>
        <propertyColumn>HMIparrent</propertyColumn>
      </AGalaxyParametr>
      <AGalaxyParametr>
        <AttributeName>SecurityDefinition</AttributeName>
        <propertyColumn>SecurityDefinition</propertyColumn>
      </AGalaxyParametr>
    </GalaxyAttributes>
  </AObjectType>
  <AObjectType>
    <DataTypeName>OnOffCtrlData_VSD</DataTypeName>
    <DataTypeSize>36</DataTypeSize>
    <FunctionName>OnOffCtrl_VSD</FunctionName>
    <Template>OnOffCtrl_VSD</Template>
    <Attributes>
      <ATopicParametr>
        <AttributeName>IFCDW0</AttributeName>
        <DataType>D0</DataType>
      </ATopicParametr>
      <ATopicParametr>
        <AttributeName>IFCDW4</AttributeName>
        <DataType>D4</DataType>
      </ATopicParametr>
      <ATopicParametr>
        <AttributeName>IFCDW8</AttributeName>
        <DataType>D8</DataType>
      </ATopicParametr>
      <ATopicParametr>
        <AttributeName>IFCW12</AttributeName>
        <DataType>W12</DataType>
      </ATopicParametr>
      <ATopicParametr>
        <AttributeName>IFCW14</AttributeName>
        <DataType>W14</DataType>
      </ATopicParametr>
      <ATopicParametr>
        <AttributeName>IFCDW16</AttributeName>
        <DataType>REAL16</DataType>
      </ATopicParametr>
      <ATopicParametr>
        <AttributeName>IFCDW20</AttributeName>
        <DataType>REAL20</DataType>
      </ATopicParametr>
    </Attributes>
    <DTProperties>
      <DataTypeProperties>
        <propertyName>IBF</propertyName>
        <propertyColumn>IBF</propertyColumn>
      </DataTypeProperties>
      <DataTypeProperties>
        <propertyName>EnAuto</propertyName>
        <propertyColumn>EnAuto</propertyColumn>
      </DataTypeProperties>
      <DataTypeProperties>
        <propertyName>LIO</propertyName>
        <propertyColumn>DBName + TagName</propertyColumn>
      </DataTypeProperties>
    </DTProperties>
    <GalaxyAttributes>
      <AGalaxyParametr>
        <AttributeName>TagName</AttributeName>
        <propertyColumn>TagName</propertyColumn>
      </AGalaxyParametr>
      <AGalaxyParametr>
        <AttributeName>ObjectDescription</AttributeName>
        <propertyColumn>Descr</propertyColumn>
      </AGalaxyParametr>
      <AGalaxyParametr>
        <AttributeName>Area</AttributeName>
        <propertyColumn>HMIArea</propertyColumn>
      </AGalaxyParametr>
      <AGalaxyParametr>
        <AttributeName>Container</AttributeName>
        <propertyColumn>HMIparrent</propertyColumn>
      </AGalaxyParametr>
      <AGalaxyParametr>
        <AttributeName>ValueDecimalPlaces</AttributeName>
        <propertyColumn>ValueDecimalPlaces</propertyColumn>
      </AGalaxyParametr>
      <AGalaxyParametr>
        <AttributeName>SecurityDefinition</AttributeName>
        <propertyColumn>SecurityDefinition</propertyColumn>
      </AGalaxyParametr>
      <AGalaxyParametr>
        <AttributeName>IFCDW20.EngUnits</AttributeName>
        <propertyColumn>Unit</propertyColumn>
      </AGalaxyParametr>
    </GalaxyAttributes>
  </AObjectType>
  <AObjectType>
    <DataTypeName>PIDCtrlData</DataTypeName>
    <DataTypeSize>140</DataTypeSize>
    <FunctionName>PID</FunctionName>
    <Template>PID</Template>
    <Attributes>
      <ATopicParametr>
        <AttributeName>IFCDW0</AttributeName>
        <DataType>D0</DataType>
      </ATopicParametr>
      <ATopicParametr>
        <AttributeName>IFCW4</AttributeName>
        <DataType>W4</DataType>
      </ATopicParametr>
      <ATopicParametr>
        <AttributeName>IFCDW6</AttributeName>
        <DataType>REAL6</DataType>
      </ATopicParametr>
      <ATopicParametr>
        <AttributeName>IFCDW10</AttributeName>
        <DataType>REAL10</DataType>
      </ATopicParametr>
      <ATopicParametr>
        <AttributeName>IFCDW14</AttributeName>
        <DataType>REAL14</DataType>
      </ATopicParametr>
      <ATopicParametr>
        <AttributeName>IFCDW18</AttributeName>
        <DataType>REAL18</DataType>
      </ATopicParametr>
      <ATopicParametr>
        <AttributeName>IFCDW22</AttributeName>
        <DataType>REAL22</DataType>
      </ATopicParametr>
      <ATopicParametr>
        <AttributeName>IFCDW26</AttributeName>
        <DataType>REAL26</DataType>
      </ATopicParametr>
      <ATopicParametr>
        <AttributeName>IFCDW30</AttributeName>
        <DataType>REAL30</DataType>
      </ATopicParametr>
      <ATopicParametr>
        <AttributeName>IFCDW34</AttributeName>
        <DataType>REAL34</DataType>
      </ATopicParametr>
      <ATopicParametr>
        <AttributeName>IFCDW38</AttributeName>
        <DataType>REAL38</DataType>
      </ATopicParametr>
      <ATopicParametr>
        <AttributeName>IFCDW42</AttributeName>
        <DataType>REAL42</DataType>
      </ATopicParametr>
      <ATopicParametr>
        <AttributeName>IFCDW46</AttributeName>
        <DataType>REAL46</DataType>
      </ATopicParametr>
    </Attributes>
    <DTProperties />
    <GalaxyAttributes>
      <AGalaxyParametr>
        <AttributeName>TagName</AttributeName>
        <propertyColumn>TagName</propertyColumn>
      </AGalaxyParametr>
      <AGalaxyParametr>
        <AttributeName>ObjectDescription</AttributeName>
        <propertyColumn>Descr</propertyColumn>
      </AGalaxyParametr>
      <AGalaxyParametr>
        <AttributeName>Area</AttributeName>
        <propertyColumn>HMIArea</propertyColumn>
      </AGalaxyParametr>
      <AGalaxyParametr>
        <AttributeName>Container</AttributeName>
        <propertyColumn>HMIparrent</propertyColumn>
      </AGalaxyParametr>
      <AGalaxyParametr>
        <AttributeName>ValueDecimalPlaces</AttributeName>
        <propertyColumn>ValueDecimalPlaces</propertyColumn>
      </AGalaxyParametr>
      <AGalaxyParametr>
        <AttributeName>SecurityDefinition</AttributeName>
        <propertyColumn>SecurityDefinition</propertyColumn>
      </AGalaxyParametr>
      <AGalaxyParametr>
        <AttributeName>IFCDW10.EngUnits</AttributeName>
        <propertyColumn>Unit</propertyColumn>
      </AGalaxyParametr>
    </GalaxyAttributes>
  </AObjectType>
  <AObjectType>
    <DataTypeName>PreselData</DataTypeName>
    <DataTypeSize>4</DataTypeSize>
    <FunctionName>Presel</FunctionName>
    <Template>Presel</Template>
    <Attributes>
      <ATopicParametr>
        <AttributeName>IFCW0</AttributeName>
        <DataType>W0</DataType>
      </ATopicParametr>
    </Attributes>
    <DTProperties>
      <DataTypeProperties>
        <propertyName>RBID</propertyName>
        <propertyColumn>RBID</propertyColumn>
      </DataTypeProperties>
      <DataTypeProperties>
        <propertyName>LIO</propertyName>
        <propertyColumn>DBName + TagName</propertyColumn>
      </DataTypeProperties>
      <DataTypeProperties>
        <propertyName>GrpLink</propertyName>
        <propertyColumn>DBName + GrpName + TagName</propertyColumn>
      </DataTypeProperties>
    </DTProperties>
    <GalaxyAttributes>
      <AGalaxyParametr>
        <AttributeName>TagName</AttributeName>
        <propertyColumn>TagName</propertyColumn>
      </AGalaxyParametr>
      <AGalaxyParametr>
        <AttributeName>ObjectDescription</AttributeName>
        <propertyColumn>Descr</propertyColumn>
      </AGalaxyParametr>
      <AGalaxyParametr>
        <AttributeName>Area</AttributeName>
        <propertyColumn>HMIArea</propertyColumn>
      </AGalaxyParametr>
      <AGalaxyParametr>
        <AttributeName>Container</AttributeName>
        <propertyColumn>HMIparrent</propertyColumn>
      </AGalaxyParametr>
      <AGalaxyParametr>
        <AttributeName>SecurityDefinition</AttributeName>
        <propertyColumn>SecurityDefinition</propertyColumn>
      </AGalaxyParametr>
    </GalaxyAttributes>
  </AObjectType>
  <AObjectType>
    <DataTypeName>Bool</DataTypeName>
    <DataTypeSize>1</DataTypeSize>
    <FunctionName>-</FunctionName>
    <Template>-</Template>
    <Attributes />
    <DTProperties />
    <GalaxyAttributes />
  </AObjectType>
  <AObjectType>
    <DataTypeName>Int</DataTypeName>
    <DataTypeSize>4</DataTypeSize>
    <FunctionName>-</FunctionName>
    <Template>-</Template>
    <Attributes />
    <DTProperties />
    <GalaxyAttributes />
  </AObjectType>
</ArrayOfAObjectType>